{
  "video_id": 25,
  "num_frames": 25,
  "image_size": [
    640,
    480
  ],
  "tracks": {
    "0": {
      "identity_id": 14,
      "start_frame": 5,
      "end_frame": 21,
      "trajectory": [
        [
          573,
          142
        ],
        [
          571,
          140
        ],
        [
          570,
          137
        ],
        [
          569,
          135
        ],
        [
          567,
          133
        ],
        [
          565,
          131
        ],
        [
          563,
          130
        ],
        [
          562,
          128
        ],
        [
          561,
          127
        ],
        [
          561,
          127
        ],
        [
          560,
          125
        ],
        [
          559,
          124
        ],
        [
          558,
          123
        ],
        [
          558,
          122
        ],
        [
          557,
          122
        ],
        [
          556,
          121
        ],
        [
          556,
          119
        ]
      ]
    },
    "1": {
      "identity_id": 14,
      "start_frame": 3,
      "end_frame": 23,
      "trajectory": [
        [
          450,
          253
        ],
        [
          451,
          253
        ],
        [
          453,
          253
        ],
        [
          454,
          254
        ],
        [
          456,
          254
        ],
        [
          458,
          255
        ],
        [
          459,
          255
        ],
        [
          460,
          254
        ],
        [
          461,
          254
        ],
        [
          462,
          254
        ],
        [
          463,
          254
        ],
        [
          464,
          254
        ],
        [
          465,
          253
        ],
        [
          466,
          252
        ],
        [
          468,
          252
        ],
        [
          470,
          251
        ],
        [
          471,
          250
        ],
        [
          472,
          250
        ],
        [
          474,
          249
        ],
        [
          474,
          248
        ],
        [
          475,
          247
        ]
      ]
    }
  },
  "frames": [
    {
      "frame_id": 0,
      "detections": []
    },
    {
      "frame_id": 1,
      "detections": []
    },
    {
      "frame_id": 2,
      "detections": []
    },
    {
      "frame_id": 3,
      "detections": [
        {
          "track_id": 1,
          "identity_id": 14,
          "bbox": [
            394,
            197,
            112,
            112
          ],
          "center": [
            450,
            253
          ],
          "confidence": 1.0
        }
      ]
    },
    {
      "frame_id": 4,
      "detections": [
        {
          "track_id": 1,
          "identity_id": 14,
          "bbox": [
            395,
            197,
            112,
            112
          ],
          "center": [
            451,
            253
          ],
          "confidence": 1.0
        }
      ]
    },
    {
      "frame_id": 5,
      "detections": [
        {
          "track_id": 0,
          "identity_id": 14,
          "bbox": [
            517,
            86,
            112,
            112
          ],
          "center": [
            573,
            142
          ],
          "confidence": 1.0
        },
        {
          "track_id": 1,
          "identity_id": 14,
          "bbox": [
            397,
            197,
            112,
            112
          ],
          "center": [
            453,
            253
          ],
          "confidence": 1.0
        }
      ]
    },
    {
      "frame_id": 6,
      "detections": [
        {
          "track_id": 0,
          "identity_id": 14,
          "bbox": [
            515,
            84,
            112,
            112
          ],
          "center": [
            571,
            140
          ],
          "confidence": 1.0
        },
        {
          "track_id": 1,
          "identity_id": 14,
          "bbox": [
            398,
            198,
            112,
            112
          ],
          "center": [
            454,
            254
          ],
          "confidence": 1.0
        }
      ]
    },
    {
      "frame_id": 7,
      "detections": [
        {
          "track_id": 0,
          "identity_id": 14,
          "bbox": [
            514,
            81,
            112,
            112
          ],
          "center": [
            570,
            137
          ],
          "confidence": 1.0
        },
        {
          "track_id": 1,
          "identity_id": 14,
          "bbox": [
            400,
            198,
            112,
            112
          ],
          "center": [
            456,
            254
          ],
          "confidence": 1.0
        }
      ]
    },
    {
      "frame_id": 8,
      "detections": [
        {
          "track_id": 0,
          "identity_id": 14,
          "bbox": [
            513,
            79,
            112,
            112
          ],
          "center": [
            569,
            135
          ],
          "confidence": 1.0
        },
        {
          "track_id": 1,
          "identity_id": 14,
          "bbox": [
            402,
            199,
            112,
            112
          ],
          "center": [
            458,
            255
          ],
          "confidence": 1.0
        }
      ]
    },
    {
      "frame_id": 9,
      "detections": [
        {
          "track_id": 0,
          "identity_id": 14,
          "bbox": [
            511,
            77,
            112,
            112
          ],
          "center": [
            567,
            133
          ],
          "confidence": 1.0
        },
        {
          "track_id": 1,
          "identity_id": 14,
          "bbox": [
            403,
            199,
            112,
            112
          ],
          "center": [
            459,
            255
          ],
          "confidence": 1.0
        }
      ]
    },
    {
      "frame_id": 10,
      "detections": [
        {
          "track_id": 0,
          "identity_id": 14,
          "bbox": [
            509,
            75,
            112,
            112
          ],
          "center": [
            565,
            131
          ],
          "confidence": 1.0
        },
        {
          "track_id": 1,
          "identity_id": 14,
          "bbox": [
            404,
            198,
            112,
            112
          ],
          "center": [
            460,
            254
          ],
          "confidence": 1.0
        }
      ]
    },
    {
      "frame_id": 11,
      "detections": [
        {
          "track_id": 0,
          "identity_id": 14,
          "bbox": [
            507,
            74,
            112,
            112
          ],
          "center": [
            563,
            130
          ],
          "confidence": 1.0
        },
        {
          "track_id": 1,
          "identity_id": 14,
          "bbox": [
            405,
            198,
            112,
            112
          ],
          "center": [
            461,
            254
          ],
          "confidence": 1.0
        }
      ]
    },
    {
      "frame_id": 12,
      "detections": [
        {
          "track_id": 0,
          "identity_id": 14,
          "bbox": [
            506,
            72,
            112,
            112
          ],
          "center": [
            562,
            128
          ],
          "confidence": 1.0
        },
        {
          "track_id": 1,
          "identity_id": 14,
          "bbox": [
            406,
            198,
            112,
            112
          ],
          "center": [
            462,
            254
          ],
          "confidence": 1.0
        }
      ]
    },
    {
      "frame_id": 13,
      "detections": [
        {
          "track_id": 0,
          "identity_id": 14,
          "bbox": [
            505,
            71,
            112,
            112
          ],
          "center": [
            561,
            127
          ],
          "confidence": 1.0
        },
        {
          "track_id": 1,
          "identity_id": 14,
          "bbox": [
            407,
            198,
            112,
            112
          ],
          "center": [
            463,
            254
          ],
          "confidence": 1.0
        }
      ]
    },
    {
      "frame_id": 14,
      "detections": [
        {
          "track_id": 0,
          "identity_id": 14,
          "bbox": [
            505,
            71,
            112,
            112
          ],
          "center": [
            561,
            127
          ],
          "confidence": 1.0
        },
        {
          "track_id": 1,
          "identity_id": 14,
          "bbox": [
            408,
            198,
            112,
            112
          ],
          "center": [
            464,
            254
          ],
          "confidence": 1.0
        }
      ]
    },
    {
      "frame_id": 15,
      "detections": [
        {
          "track_id": 0,
          "identity_id": 14,
          "bbox": [
            504,
            69,
            112,
            112
          ],
          "center": [
            560,
            125
          ],
          "confidence": 1.0
        },
        {
          "track_id": 1,
          "identity_id": 14,
          "bbox": [
            409,
            197,
            112,
            112
          ],
          "center": [
            465,
            253
          ],
          "confidence": 1.0
        }
      ]
    },
    {
      "frame_id": 16,
      "detections": [
        {
          "track_id": 0,
          "identity_id": 14,
          "bbox": [
            503,
            68,
            112,
            112
          ],
          "center": [
            559,
            124
          ],
          "confidence": 1.0
        },
        {
          "track_id": 1,
          "identity_id": 14,
          "bbox": [
            410,
            196,
            112,
            112
          ],
          "center": [
            466,
            252
          ],
          "confidence": 1.0
        }
      ]
    },
    {
      "frame_id": 17,
      "detections": [
        {
          "track_id": 0,
          "identity_id": 14,
          "bbox": [
            502,
            67,
            112,
            112
          ],
          "center": [
            558,
            123
          ],
          "confidence": 1.0
        },
        {
          "track_id": 1,
          "identity_id": 14,
          "bbox": [
            412,
            196,
            112,
            112
          ],
          "center": [
            468,
            252
          ],
          "confidence": 1.0
        }
      ]
    },
    {
      "frame_id": 18,
      "detections": [
        {
          "track_id": 0,
          "identity_id": 14,
          "bbox": [
            502,
            66,
            112,
            112
          ],
          "center": [
            558,
            122
          ],
          "confidence": 1.0
        },
        {
          "track_id": 1,
          "identity_id": 14,
          "bbox": [
            414,
            195,
            112,
            112
          ],
          "center": [
            470,
            251
          ],
          "confidence": 1.0
        }
      ]
    },
    {
      "frame_id": 19,
      "detections": [
        {
          "track_id": 0,
          "identity_id": 14,
          "bbox": [
            501,
            66,
            112,
            112
          ],
          "center": [
            557,
            122
          ],
          "confidence": 1.0
        },
        {
          "track_id": 1,
          "identity_id": 14,
          "bbox": [
            415,
            194,
            112,
            112
          ],
          "center": [
            471,
            250
          ],
          "confidence": 1.0
        }
      ]
    },
    {
      "frame_id": 20,
      "detections": [
        {
          "track_id": 0,
          "identity_id": 14,
          "bbox": [
            500,
            65,
            112,
            112
          ],
          "center": [
            556,
            121
          ],
          "confidence": 1.0
        },
        {
          "track_id": 1,
          "identity_id": 14,
          "bbox": [
            416,
            194,
            112,
            112
          ],
          "center": [
            472,
            250
          ],
          "confidence": 1.0
        }
      ]
    },
    {
      "frame_id": 21,
      "detections": [
        {
          "track_id": 0,
          "identity_id": 14,
          "bbox": [
            500,
            63,
            112,
            112
          ],
          "center": [
            556,
            119
          ],
          "confidence": 1.0
        },
        {
          "track_id": 1,
          "identity_id": 14,
          "bbox": [
            418,
            193,
            112,
            112
          ],
          "center": [
            474,
            249
          ],
          "confidence": 1.0
        }
      ]
    },
    {
      "frame_id": 22,
      "detections": [
        {
          "track_id": 1,
          "identity_id": 14,
          "bbox": [
            418,
            192,
            112,
            112
          ],
          "center": [
            474,
            248
          ],
          "confidence": 1.0
        }
      ]
    },
    {
      "frame_id": 23,
      "detections": [
        {
          "track_id": 1,
          "identity_id": 14,
          "bbox": [
            419,
            191,
            112,
            112
          ],
          "center": [
            475,
            247
          ],
          "confidence": 1.0
        }
      ]
    },
    {
      "frame_id": 24,
      "detections": []
    }
  ]
}